{
  "ticker": "BA",
  "articles": [
    {
      "headline": "Boeing (BA) Outpaces Stock Market Gains: What You Should Know",
      "source": "Yahoo",
      "url": "https://finnhub.io/api/news?id=dc7d11934f516fbf855a70acc52d449d429afd53bbaf648112f25082aa5473b8",
      "published_at": "2026-03-23T21:45:03",
      "sentiment": "neutral",
      "sentiment_score": 0.0,
      "sentiment_confidence": 0.774,
      "relevance_score": 1.0,
      "event_type": null
    },
    {
      "headline": "The Boeing Company (BA) Secures 777 FAA Node Amid Soaring Demand",
      "source": "Yahoo",
      "url": "https://finnhub.io/api/news?id=11bac7dd06ff01175c3880de32539b80413da617b290bd8a76f16eb901b0a55b",
      "published_at": "2026-03-23T18:40:31",
      "sentiment": "positive",
      "sentiment_score": 0.942,
      "sentiment_confidence": 0.942,
      "relevance_score": 1.0,
      "event_type": null
    },
    {
      "headline": "Boeing vs Honeywell vs 3M: Which Dip Is the Best Buy Right Now?",
      "source": "Yahoo",
      "url": "https://finnhub.io/api/news?id=f4caa1285f015fa61c195772d204f1f5af8707fb3a54fbe88bbe034ab07c1415",
      "published_at": "2026-03-23T15:35:25",
      "sentiment": "neutral",
      "sentiment_score": 0.0,
      "sentiment_confidence": 0.912,
      "relevance_score": 1.0,
      "event_type": null
    },
    {
      "headline": "Boeing vs. General Dynamics: Which Aerospace Stock Is the Better Bet?",
      "source": "Yahoo",
      "url": "https://finnhub.io/api/news?id=c89aa0dc0730462f0bf4b04d506a7b6c0c6f96487ee5b8bdaeb3857417e133c0",
      "published_at": "2026-03-23T15:27:00",
      "sentiment": "neutral",
      "sentiment_score": 0.0,
      "sentiment_confidence": 0.908,
      "relevance_score": 1.0,
      "event_type": null
    },
    {
      "headline": "Could This Be China\u2019s Strategy To Paralyze the Pentagon?",
      "source": "Yahoo",
      "url": "https://finnhub.io/api/news?id=7e874c241fb6419ae4bbd43873d3c636b1533e3ddc0ace1b573816e727b214f9",
      "published_at": "2026-03-23T14:38:00",
      "sentiment": "neutral",
      "sentiment_score": 0.0,
      "sentiment_confidence": 0.78,
      "relevance_score": 1.0,
      "event_type": null
    },
    {
      "headline": "Wall Street Lunch: Markets Flip After Trump's Iran Pivot",
      "source": "SeekingAlpha",
      "url": "https://finnhub.io/api/news?id=d018a50bb1eca5f241b127d703573b849a29e54f21ce9c8112643d8262e64e41",
      "published_at": "2026-03-23T12:49:56",
      "sentiment": "neutral",
      "sentiment_score": 0.0,
      "sentiment_confidence": 0.554,
      "relevance_score": 1.0,
      "event_type": null
    },
    {
      "headline": "Albany International CFO Breaks Down AEC Q4 Surge, Warns Gains Won\u2019t Repeat at JPMorgan Conference",
      "source": "Yahoo",
      "url": "https://finnhub.io/api/news?id=bdf46839213884244854b7358fe9aa9335395202697a7cb8d6067c9b4b9dd018",
      "published_at": "2026-03-23T10:17:21",
      "sentiment": "negative",
      "sentiment_score": -0.576,
      "sentiment_confidence": 0.576,
      "relevance_score": 1.0,
      "event_type": null
    },
    {
      "headline": "'Ground Stop In Place, Control Tower Evacuated At Newark Airport After Reports Of Smoke' - ABC News",
      "source": "Benzinga",
      "url": "https://finnhub.io/api/news?id=fa6df4f9543c21f31cdaaf054de8c8760faa76df284ea4201f0bce459ec68a8c",
      "published_at": "2026-03-23T08:16:36",
      "sentiment": "negative",
      "sentiment_score": -0.902,
      "sentiment_confidence": 0.902,
      "relevance_score": 1.0,
      "event_type": null
    },
    {
      "headline": "The Boeing Company (BA) Eyes Strong Recovery as Backlog Surges and Margins Stabilize",
      "source": "Yahoo",
      "url": "https://finnhub.io/api/news?id=151e946a3044e102b4d46c39b72d85476029d4f6c28307eb8fcd4f301f5cf641",
      "published_at": "2026-03-22T16:53:22",
      "sentiment": "positive",
      "sentiment_score": 0.95,
      "sentiment_confidence": 0.95,
      "relevance_score": 1.0,
      "event_type": null
    },
    {
      "headline": "SpaceX Will Be Even More Profitable After Its 2026 IPO",
      "source": "Yahoo",
      "url": "https://finnhub.io/api/news?id=e0237a6d8f7d00bd0e5eec85a631a64317a36c479df5329e2d28de5b2f2cd06f",
      "published_at": "2026-03-22T09:25:00",
      "sentiment": "positive",
      "sentiment_score": 0.849,
      "sentiment_confidence": 0.849,
      "relevance_score": 1.0,
      "event_type": null
    },
    {
      "headline": "2 Top Defense Stocks to Buy Now as the Military Works to Reopen the Strait of Hormuz",
      "source": "Yahoo",
      "url": "https://finnhub.io/api/news?id=8ced6c3114da5dbff468a270a4ddfcea347a8510ae184ba3852e09a6b38edcba",
      "published_at": "2026-03-21T14:00:02",
      "sentiment": "positive",
      "sentiment_score": 0.604,
      "sentiment_confidence": 0.604,
      "relevance_score": 1.0,
      "event_type": null
    },
    {
      "headline": "U.K. says Iran unsuccessfully targeted British-American Diego Garcia base",
      "source": "CNBC",
      "url": "https://finnhub.io/api/news?id=412ed6ed2098842de2a6758f0ce4c9f46069a9c7dc30286bff62b5fdccc738d9",
      "published_at": "2026-03-21T04:31:50",
      "sentiment": "negative",
      "sentiment_score": -0.78,
      "sentiment_confidence": 0.78,
      "relevance_score": 1.0,
      "event_type": null
    },
    {
      "headline": "Boeing\u2019s Reduced Artemis Role And What It Could Mean For NYSE BA Investors",
      "source": "Yahoo",
      "url": "https://finnhub.io/api/news?id=81b8fe2e7fc49c46d0bb91f1a9158e3b1532ea55e890d75462252f93162e5f02",
      "published_at": "2026-03-21T01:03:51",
      "sentiment": "negative",
      "sentiment_score": -0.924,
      "sentiment_confidence": 0.924,
      "relevance_score": 1.0,
      "event_type": null
    },
    {
      "headline": "This Aerospace Stock Tests Support Amid Iran War, Eyes Fresh Entry As It Soars 18%",
      "source": "Yahoo",
      "url": "https://finnhub.io/api/news?id=ca8851a8af8b1cc46e86b296d8c63ec664c25d78f1f0ad764d805a28fc11cfee",
      "published_at": "2026-03-20T17:09:29",
      "sentiment": "positive",
      "sentiment_score": 0.931,
      "sentiment_confidence": 0.931,
      "relevance_score": 1.0,
      "event_type": null
    },
    {
      "headline": "Trump says he doesn't want Iran war ceasefire, but is considering 'winding down' military ops",
      "source": "CNBC",
      "url": "https://finnhub.io/api/news?id=c8dec6b2702daacc555b83769f4cd2542c2fc50272eede22792fd5a172f01ec9",
      "published_at": "2026-03-20T15:48:38",
      "sentiment": "negative",
      "sentiment_score": -0.717,
      "sentiment_confidence": 0.717,
      "relevance_score": 1.0,
      "event_type": null
    },
    {
      "headline": "Boeing: The Triple Blow",
      "source": "SeekingAlpha",
      "url": "https://finnhub.io/api/news?id=8bcc311f3795632654f5bd37d71034b06c3e0469aecb705ac6a83a30f7bd4717",
      "published_at": "2026-03-20T12:43:15",
      "sentiment": "neutral",
      "sentiment_score": 0.0,
      "sentiment_confidence": 0.902,
      "relevance_score": 1.0,
      "event_type": null
    },
    {
      "headline": "IFQM'S FIRST MSME SYMPOSIUM CALLS FOR A 'NATIONAL QUALITY SPRINT' TO INTEGRATE WITH GLOBAL VALUE CHAINS",
      "source": "Yahoo",
      "url": "https://finnhub.io/api/news?id=43e384b8c353e0ff0d832ddbfc27df30dec65dab84bf7b075b3b335b355f11da",
      "published_at": "2026-03-20T12:13:00",
      "sentiment": "neutral",
      "sentiment_score": 0.0,
      "sentiment_confidence": 0.515,
      "relevance_score": 1.0,
      "event_type": null
    },
    {
      "headline": "Trump: U.S. could end Iran military operations 'right now' but will continue so Iran can 'never rebuild'",
      "source": "CNBC",
      "url": "https://finnhub.io/api/news?id=39a53a508d4c853e40fc463d437e8564ea06e17ca16f960594fb81e9b78bb4a9",
      "published_at": "2026-03-20T12:10:43",
      "sentiment": "negative",
      "sentiment_score": -0.597,
      "sentiment_confidence": 0.597,
      "relevance_score": 1.0,
      "event_type": null
    },
    {
      "headline": "Market Chatter: Lockheed Martin, Boeing Part of $23 Billion Arms Sale to Gulf Allies",
      "source": "Yahoo",
      "url": "https://finnhub.io/api/news?id=457e8a57553778af4be5bd8baf6578a199282a2c809d23442eea1a76c1375057",
      "published_at": "2026-03-20T09:18:32",
      "sentiment": "neutral",
      "sentiment_score": 0.0,
      "sentiment_confidence": 0.856,
      "relevance_score": 1.0,
      "event_type": null
    },
    {
      "headline": "Trump invokes emergency powers with $23 billion in Gulf arms sales as Iran war wages on: WSJ report",
      "source": "CNBC",
      "url": "https://finnhub.io/api/news?id=efca0d58d3b1f749853a9c914f7f743675df77ed088862d235ef52db14ac1298",
      "published_at": "2026-03-20T03:35:51",
      "sentiment": "neutral",
      "sentiment_score": 0.0,
      "sentiment_confidence": 0.809,
      "relevance_score": 1.0,
      "event_type": null
    },
    {
      "headline": "US Equity Indexes Off Session Lows After Trump Warns Iran Over Qatar",
      "source": "Yahoo",
      "url": "https://finnhub.io/api/news?id=43ea30273136665f19e50c9769b9467aecbf4b4611a2af823e7b1bf704a8d855",
      "published_at": "2026-03-19T21:48:39",
      "sentiment": "negative",
      "sentiment_score": -0.865,
      "sentiment_confidence": 0.865,
      "relevance_score": 1.0,
      "event_type": null
    },
    {
      "headline": "Stock Market Today, March 19: Brent Crude's $119 Spike Rattles Markets",
      "source": "Yahoo",
      "url": "https://finnhub.io/api/news?id=d7e496923fc0820ad90aa2cb580cbabadd16cae466e6269a8b601bbdf3cb7670",
      "published_at": "2026-03-19T21:39:22",
      "sentiment": "negative",
      "sentiment_score": -0.926,
      "sentiment_confidence": 0.926,
      "relevance_score": 1.0,
      "event_type": null
    },
    {
      "headline": "Pentagon Seeks $200 Billion for Iran War. Here\u2019s What It Means for Defense Stocks.",
      "source": "Yahoo",
      "url": "https://finnhub.io/api/news?id=4c540ca597c980329ddac72f8d73ba47ea3dcb36998ff6b832948bde902a41fb",
      "published_at": "2026-03-19T20:21:00",
      "sentiment": "neutral",
      "sentiment_score": 0.0,
      "sentiment_confidence": 0.943,
      "relevance_score": 1.0,
      "event_type": null
    },
    {
      "headline": "Market Chatter: Boeing Faces Reduced Role in NASA Moon Mission",
      "source": "Yahoo",
      "url": "https://finnhub.io/api/news?id=b9452423081c85e58e09a8b304fc5616cb2789373f1d2dad4c6d59a2533f823a",
      "published_at": "2026-03-19T19:29:44",
      "sentiment": "negative",
      "sentiment_score": -0.928,
      "sentiment_confidence": 0.928,
      "relevance_score": 1.0,
      "event_type": null
    },
    {
      "headline": "Is\u00a0The Boeing Company (BA)\u00a0A Good Stock\u00a0To\u00a0Buy Now?",
      "source": "Yahoo",
      "url": "https://finnhub.io/api/news?id=6066f39766ad9cd12d8fc8f18c4e503ca9a17c6526a20dbe4aa70bdbe554e4a9",
      "published_at": "2026-03-19T17:14:24",
      "sentiment": "neutral",
      "sentiment_score": 0.0,
      "sentiment_confidence": 0.864,
      "relevance_score": 1.0,
      "event_type": null
    },
    {
      "headline": "Defense Stocks Are Surging and This ETF Lets You Collect Dividends From the Global Arms Race",
      "source": "Yahoo",
      "url": "https://finnhub.io/api/news?id=0dd79423c93199fd2aa14e31a46a029708119204bf5d78d23dd61c683fb8bc63",
      "published_at": "2026-03-19T16:05:20",
      "sentiment": "neutral",
      "sentiment_score": 0.0,
      "sentiment_confidence": 0.82,
      "relevance_score": 1.0,
      "event_type": null
    },
    {
      "headline": "Netanyahu says Iran is being 'decimated' but revolution requires 'ground component'",
      "source": "CNBC",
      "url": "https://finnhub.io/api/news?id=b5ce74498b363aa48882e773ccc70bde69d9375d8c405a666ee6356b6cc77eff",
      "published_at": "2026-03-19T16:01:23",
      "sentiment": "neutral",
      "sentiment_score": 0.0,
      "sentiment_confidence": 0.807,
      "relevance_score": 1.0,
      "event_type": null
    },
    {
      "headline": "Market Madness: Why JPMorgan, McDonald's are slam dunk stock picks",
      "source": "Yahoo",
      "url": "https://finnhub.io/api/news?id=a568041b67489f8605705050829cafa000c64d6771c65c666c86ffd1636f3af6",
      "published_at": "2026-03-19T16:00:00",
      "sentiment": "neutral",
      "sentiment_score": 0.0,
      "sentiment_confidence": 0.857,
      "relevance_score": 1.0,
      "event_type": null
    },
    {
      "headline": "Defense Stocks Show Clear Winners, Losers Amid Ongoing U.S.-Iran Conflict",
      "source": "Yahoo",
      "url": "https://finnhub.io/api/news?id=9cf7f4854405cde5bbb7873a6fde373bec56b58dea4d9b6892416f5cc76ca05b",
      "published_at": "2026-03-19T15:56:47",
      "sentiment": "negative",
      "sentiment_score": -0.968,
      "sentiment_confidence": 0.968,
      "relevance_score": 1.0,
      "event_type": null
    },
    {
      "headline": "Tigress Financial Maintains Buy on Boeing, Raises Price Target to $290",
      "source": "Benzinga",
      "url": "https://finnhub.io/api/news?id=1ea6de836e4b67de5231c4f597edfdf9123924ebb0e4a19fd0ae1d1f414e9dc0",
      "published_at": "2026-03-19T15:14:56",
      "sentiment": "positive",
      "sentiment_score": 0.889,
      "sentiment_confidence": 0.889,
      "relevance_score": 1.0,
      "event_type": null
    },
    {
      "headline": "'NASA Plans Bigger SpaceX Moon-Mission Role in Blow to Boeing'- Bloomberg",
      "source": "Benzinga",
      "url": "https://finnhub.io/api/news?id=6d51306cdc72b94fd732081f328b0d47ae824135724eea8bb9002cb160a1b6fa",
      "published_at": "2026-03-19T14:20:50",
      "sentiment": "neutral",
      "sentiment_score": 0.0,
      "sentiment_confidence": 0.773,
      "relevance_score": 1.0,
      "event_type": null
    },
    {
      "headline": "Private Credit's $1.8 Trillion Illusion Breaks: The Liquidity Crunch No One Was Ready For",
      "source": "Benzinga",
      "url": "https://finnhub.io/api/news?id=15acf53f5896e47fe92d55455467774d305ce1f42528759d90ebf8892640586a",
      "published_at": "2026-03-19T13:05:36",
      "sentiment": "negative",
      "sentiment_score": -0.885,
      "sentiment_confidence": 0.885,
      "relevance_score": 1.0,
      "event_type": null
    },
    {
      "headline": "SBA Celebrates Success of First-Ever Made In America Matchmaking Expo for Suppliers and Manufacturers",
      "source": "Yahoo",
      "url": "https://finnhub.io/api/news?id=1d9a0d6f9f2d36f48af721e36cce636cac002b7243e529767fcad45ef9fa0cf7",
      "published_at": "2026-03-19T13:00:00",
      "sentiment": "positive",
      "sentiment_score": 0.836,
      "sentiment_confidence": 0.836,
      "relevance_score": 1.0,
      "event_type": null
    },
    {
      "headline": "United Airlines' Inaugural Flight On Boeing 787-9 Dreamliner Set To Fly From San Francisco To Singapore On April 22",
      "source": "Benzinga",
      "url": "https://finnhub.io/api/news?id=5e8b7a8c554d108ed79037efb003f78797168f0a653e13b31e40ce643db08f7a",
      "published_at": "2026-03-19T10:04:35",
      "sentiment": "neutral",
      "sentiment_score": 0.0,
      "sentiment_confidence": 0.719,
      "relevance_score": 1.0,
      "event_type": null
    },
    {
      "headline": "Hegseth says potential $200 billion Iran war spending request could shift: 'Takes money to kill bad guys'",
      "source": "CNBC",
      "url": "https://finnhub.io/api/news?id=4dcbc1a3763b8c4b66a9b134d9e0171f992d4a74afcf1b3c04797a46811d051c",
      "published_at": "2026-03-19T08:44:14",
      "sentiment": "neutral",
      "sentiment_score": 0.0,
      "sentiment_confidence": 0.445,
      "relevance_score": 1.0,
      "event_type": null
    },
    {
      "headline": "Private credit defense borrowers set to benefit from munition replenishment",
      "source": "Yahoo",
      "url": "https://finnhub.io/api/news?id=279bc039e80aef3f3713a17998d2c9f2753f7dd5d682a24bf0db111aa142dab7",
      "published_at": "2026-03-18T18:48:48",
      "sentiment": "positive",
      "sentiment_score": 0.62,
      "sentiment_confidence": 0.62,
      "relevance_score": 1.0,
      "event_type": null
    },
    {
      "headline": "Boeing (BA) Secures $489.31M Contract From The Naval Air Systems Command",
      "source": "Yahoo",
      "url": "https://finnhub.io/api/news?id=862bb40450e44543b14af05f0158d36c09d2216ce763801f51d9108219d766ae",
      "published_at": "2026-03-18T16:56:44",
      "sentiment": "positive",
      "sentiment_score": 0.932,
      "sentiment_confidence": 0.932,
      "relevance_score": 1.0,
      "event_type": null
    },
    {
      "headline": "Boeing\u2019s 737 MAX Wiring Issue Is a Minor Hiccup. These Are the Real Threats.",
      "source": "MarketWatch",
      "url": "https://finnhub.io/api/news?id=dd300940ae9549a018ab1a6edf1dc99e357a926d7eec2cd0689574780c111533",
      "published_at": "2026-03-18T16:17:00",
      "sentiment": "neutral",
      "sentiment_score": 0.0,
      "sentiment_confidence": 0.676,
      "relevance_score": 1.0,
      "event_type": null
    },
    {
      "headline": "10 Industrials Stocks With Whale Alerts In Today's Session",
      "source": "Benzinga",
      "url": "https://finnhub.io/api/news?id=cf4c09714a09dbd5c35bea628876160607a923b75686a3afe1ea10bbf7d8116e",
      "published_at": "2026-03-18T13:35:19",
      "sentiment": "neutral",
      "sentiment_score": 0.0,
      "sentiment_confidence": 0.864,
      "relevance_score": 1.0,
      "event_type": null
    },
    {
      "headline": "Investors Heavily Search The Boeing Company (BA): Here is What You Need to Know",
      "source": "Yahoo",
      "url": "https://finnhub.io/api/news?id=719dfff37c17ee30ace996806afb312f97787b1378172e18a66ca4912edeefb1",
      "published_at": "2026-03-18T13:00:05",
      "sentiment": "neutral",
      "sentiment_score": 0.0,
      "sentiment_confidence": 0.938,
      "relevance_score": 1.0,
      "event_type": null
    },
    {
      "headline": "'FAA Clears Boeing 777-9 To Begin First Part Of TIA Phase 4 Certification Trials' - Air Current",
      "source": "Benzinga",
      "url": "https://finnhub.io/api/news?id=6a92cddc689ee686f73f664a2a2485ae2b6d8db82d185ad9bdb309ae5a52cae6",
      "published_at": "2026-03-18T12:52:25",
      "sentiment": "neutral",
      "sentiment_score": 0.0,
      "sentiment_confidence": 0.733,
      "relevance_score": 1.0,
      "event_type": null
    },
    {
      "headline": "The U.S. Army\u2019s $20B Anduril Deal Points to Upside for Palantir, Lockheed Martin, and Defense Tech Stocks",
      "source": "Yahoo",
      "url": "https://finnhub.io/api/news?id=71be7f7723123a249f75860eefafc826991c8707da03d6d04a5cdc08d4d76ce7",
      "published_at": "2026-03-18T12:39:14",
      "sentiment": "positive",
      "sentiment_score": 0.943,
      "sentiment_confidence": 0.943,
      "relevance_score": 1.0,
      "event_type": null
    },
    {
      "headline": "Boeing Seen Steady On Production, Defense Upside Despite Near-Term Margin Pressure, Says BofA Analyst",
      "source": "Benzinga",
      "url": "https://finnhub.io/api/news?id=cd914524f5010869a9952cf217b85a5e8eb34eb1ba2a692d25496cca4149dd7d",
      "published_at": "2026-03-18T12:03:28",
      "sentiment": "positive",
      "sentiment_score": 0.926,
      "sentiment_confidence": 0.926,
      "relevance_score": 1.0,
      "event_type": null
    },
    {
      "headline": "Astronics Wins Boeing 737 MAX Contract As Aerospace Exposure Deepens",
      "source": "Yahoo",
      "url": "https://finnhub.io/api/news?id=ea3df388cca0896f21f4c66945afea465ef911a5eb01441a5b0e0d641bf840dd",
      "published_at": "2026-03-18T10:04:34",
      "sentiment": "positive",
      "sentiment_score": 0.938,
      "sentiment_confidence": 0.938,
      "relevance_score": 1.0,
      "event_type": null
    },
    {
      "headline": "Boeing: Ignore Fuel Price Spikes For This Decade Play",
      "source": "SeekingAlpha",
      "url": "https://finnhub.io/api/news?id=db051d22c381cb88c651724f6e8ea7d4ae01f15bb42f629c18b892cd41b4576a",
      "published_at": "2026-03-18T09:30:08",
      "sentiment": "neutral",
      "sentiment_score": 0.0,
      "sentiment_confidence": 0.881,
      "relevance_score": 1.0,
      "event_type": null
    },
    {
      "headline": "Honeywell International CEO Reaffirms Outlook, Flags Middle East Shipping Disruptions at Conference",
      "source": "Yahoo",
      "url": "https://finnhub.io/api/news?id=003a193595c3806d0f93b7c4743d162be517f0fb096e82331213359bad50add6",
      "published_at": "2026-03-18T08:25:27",
      "sentiment": "negative",
      "sentiment_score": -0.82,
      "sentiment_confidence": 0.82,
      "relevance_score": 1.0,
      "event_type": null
    },
    {
      "headline": "Atlas Air Airbus Shift Tests Confidence In Boeing Widebody Freighters",
      "source": "Yahoo",
      "url": "https://finnhub.io/api/news?id=d1d5327a6d047ea7293178e2b8ba22673a44a3f4f9679717bb891b803b14e180",
      "published_at": "2026-03-18T06:17:03",
      "sentiment": "positive",
      "sentiment_score": 0.665,
      "sentiment_confidence": 0.665,
      "relevance_score": 1.0,
      "event_type": null
    },
    {
      "headline": "Trump's Golden Dome Cost Surges To $185 Billion As Space-Based Missile Defense Takes Center Stage",
      "source": "Benzinga",
      "url": "https://finnhub.io/api/news?id=fa6c456c2df5b24cd896591fe5830a1334775d602f62b70d08e317ec749b727f",
      "published_at": "2026-03-18T03:48:42",
      "sentiment": "positive",
      "sentiment_score": 0.897,
      "sentiment_confidence": 0.897,
      "relevance_score": 1.0,
      "event_type": null
    },
    {
      "headline": "Boeing Expects Challenges From Absorption of Spirit AeroSystems",
      "source": "Yahoo",
      "url": "https://finnhub.io/api/news?id=7e6adfacc484fb5963077e9f59bd96eba08ca4be63d67ba6e41c498b2bfb8860",
      "published_at": "2026-03-17T21:06:51",
      "sentiment": "negative",
      "sentiment_score": -0.8,
      "sentiment_confidence": 0.8,
      "relevance_score": 1.0,
      "event_type": null
    },
    {
      "headline": "Constellium, IBD Stock Of The Day, Forges Bullish Entry After 72% Rally Amid Accelerating Growth",
      "source": "Yahoo",
      "url": "https://finnhub.io/api/news?id=dc28cd1893bb1a8b64766665d634e093546d39f71bd0dd93ca45caed6905fb29",
      "published_at": "2026-03-17T17:41:31",
      "sentiment": "positive",
      "sentiment_score": 0.937,
      "sentiment_confidence": 0.937,
      "relevance_score": 1.0,
      "event_type": null
    }
  ]
}