{
  "ticker": "NKE",
  "articles": [
    {
      "headline": "Nike Cutting 1,400 More Jobs. The Stock Is Rising.",
      "source": "Yahoo",
      "url": "https://finnhub.io/api/news?id=dec8acbf4b22acaf712011ef10322cb2a6a9c83f8f6a4f40bd084424f4273625",
      "published_at": "2026-04-23T21:30:00",
      "sentiment": "negative",
      "sentiment_score": -0.483,
      "sentiment_confidence": 0.483,
      "relevance_score": 1.0,
      "event_type": null
    },
    {
      "headline": "Nike Cuts 1,400 Jobs in Operations and Tech in Latest Round of Layoffs",
      "source": "Yahoo",
      "url": "https://finnhub.io/api/news?id=26a66b8cb87a0a12e2ed5f6c1f740ba5f0cdf4b82b438845e139e8e7b7cd4743",
      "published_at": "2026-04-23T21:25:29",
      "sentiment": "negative",
      "sentiment_score": -0.97,
      "sentiment_confidence": 0.97,
      "relevance_score": 1.0,
      "event_type": null
    },
    {
      "headline": "Nike cutting 1,400 jobs in latest round of layoffs",
      "source": "Yahoo",
      "url": "https://finnhub.io/api/news?id=7dcc73f12d96b7bf252a397f1b7528a46f775bd83102f914219b155cd022a61e",
      "published_at": "2026-04-23T21:18:15",
      "sentiment": "negative",
      "sentiment_score": -0.97,
      "sentiment_confidence": 0.97,
      "relevance_score": 1.0,
      "event_type": null
    },
    {
      "headline": "Is Nike\u2019s Next Focus an Expanded Presence in Team Sports?",
      "source": "Yahoo",
      "url": "https://finnhub.io/api/news?id=0af8e5fe7e7f30ee7259e4b483eff9906f56570b4deb338ce5db7e445550128a",
      "published_at": "2026-04-23T20:51:33",
      "sentiment": "neutral",
      "sentiment_score": 0.0,
      "sentiment_confidence": 0.807,
      "relevance_score": 1.0,
      "event_type": null
    },
    {
      "headline": "Jim Cramer Shares Hot Take on Nike (NKE) & Elliott Vs Elliott",
      "source": "Yahoo",
      "url": "https://finnhub.io/api/news?id=70d0990d01c884cc15039b4027a938694443f3a104d35195b0adbf13c01c6095",
      "published_at": "2026-04-23T19:37:23",
      "sentiment": "positive",
      "sentiment_score": 0.497,
      "sentiment_confidence": 0.497,
      "relevance_score": 1.0,
      "event_type": null
    },
    {
      "headline": "Lululemon CEO Pick Heidi O\u2019Neill Faces Skeptical Wall Street",
      "source": "Yahoo",
      "url": "https://finnhub.io/api/news?id=04306ab50184568d13ea11bd0883d4ce5d907b3ee24461b0933410405647a1f3",
      "published_at": "2026-04-23T19:35:12",
      "sentiment": "negative",
      "sentiment_score": -0.87,
      "sentiment_confidence": 0.87,
      "relevance_score": 1.0,
      "event_type": null
    },
    {
      "headline": "NIKE : Announces Global Operations Changes",
      "source": "Finnhub",
      "url": "https://finnhub.io/api/news?id=3f82272ef6c1dc24b9f8bd41aa23d4c1f4f179d36e0bccb514104047463f8d00",
      "published_at": "2026-04-23T17:28:34",
      "sentiment": "neutral",
      "sentiment_score": 0.0,
      "sentiment_confidence": 0.919,
      "relevance_score": 1.0,
      "event_type": null
    },
    {
      "headline": "Nike to cut around 1,400 jobs in efficiency push",
      "source": "Finnhub",
      "url": "https://finnhub.io/api/news?id=cd3872b790346833d5220d4001c3694f314cf93ad0bb6cdd4638a5e9d406dccf",
      "published_at": "2026-04-23T16:58:19",
      "sentiment": "negative",
      "sentiment_score": -0.953,
      "sentiment_confidence": 0.953,
      "relevance_score": 1.0,
      "event_type": null
    },
    {
      "headline": "'Nike Cuts 1,400 Roles In Second Round Of Layoffs This Year' - CNBC",
      "source": "Benzinga",
      "url": "https://finnhub.io/api/news?id=8cca6979480e1433f4ad053ecc69467d2e905ae64411186de046e63b775dd6aa",
      "published_at": "2026-04-23T16:51:07",
      "sentiment": "negative",
      "sentiment_score": -0.959,
      "sentiment_confidence": 0.959,
      "relevance_score": 1.0,
      "event_type": null
    },
    {
      "headline": "Nike Is Now the Third Highest-Yielding Dividend Stock in the Dow Jones Industrial Average. Should You Follow Apple CEO Tim Cook's Lead and Buy Nike Near a 10-Year Low?",
      "source": "Yahoo",
      "url": "https://finnhub.io/api/news?id=b8800c01c02aa7590797e7da1804e8269926270886a39f35e8c7c72b8e57708b",
      "published_at": "2026-04-23T16:50:00",
      "sentiment": "neutral",
      "sentiment_score": 0.0,
      "sentiment_confidence": 0.54,
      "relevance_score": 1.0,
      "event_type": null
    },
    {
      "headline": "Nike to cut 1,400 jobs",
      "source": "Finnhub",
      "url": "https://finnhub.io/api/news?id=1dcb929a027d616e833cff3e4bab1dbb9734278d45cb2fcdef16e6aab3e700c8",
      "published_at": "2026-04-23T16:41:54",
      "sentiment": "negative",
      "sentiment_score": -0.954,
      "sentiment_confidence": 0.954,
      "relevance_score": 1.0,
      "event_type": null
    },
    {
      "headline": "Nike says co to reduce around 1,400 roles in global operations - company statement",
      "source": "Finnhub",
      "url": "https://finnhub.io/api/news?id=7f70a0c4ebeef9f7e94d5f341eca3b4851e823aa37728d5a1eb2c13e826a5dd6",
      "published_at": "2026-04-23T16:39:59",
      "sentiment": "negative",
      "sentiment_score": -0.714,
      "sentiment_confidence": 0.714,
      "relevance_score": 1.0,
      "event_type": null
    },
    {
      "headline": "Nike: reduction of approximately 1,400 roles in global operations - company statement",
      "source": "Finnhub",
      "url": "https://finnhub.io/api/news?id=ce7ccde0a8105457913fbb8db2ff550786667b8626053da91a1c62009a55e572",
      "published_at": "2026-04-23T16:39:18",
      "sentiment": "negative",
      "sentiment_score": -0.92,
      "sentiment_confidence": 0.92,
      "relevance_score": 1.0,
      "event_type": null
    },
    {
      "headline": "Lululemon shares drop after CEO change amplifies ongoing brand reset efforts",
      "source": "Yahoo",
      "url": "https://finnhub.io/api/news?id=0a0e569c0d3492e958d1f3cfec24aa17de4fb9437518ae6297dd656d2b8bd2dd",
      "published_at": "2026-04-23T16:37:00",
      "sentiment": "negative",
      "sentiment_score": -0.97,
      "sentiment_confidence": 0.97,
      "relevance_score": 1.0,
      "event_type": null
    },
    {
      "headline": "Nike cuts 1,400 roles in second round of layoffs this year - CNBC",
      "source": "Finnhub",
      "url": "https://finnhub.io/api/news?id=e11024d5269db004db88a0d2e7b06dcbae055b9a18aea29e7526cec4014f738e",
      "published_at": "2026-04-23T16:36:16",
      "sentiment": "negative",
      "sentiment_score": -0.954,
      "sentiment_confidence": 0.954,
      "relevance_score": 1.0,
      "event_type": null
    },
    {
      "headline": "Lululemon investors sour on new CEO pick as the stock sinks",
      "source": "Yahoo",
      "url": "https://finnhub.io/api/news?id=2b692a9a30b4efb60e734033adee804160062c59b4e021571722695c8b3ac9b3",
      "published_at": "2026-04-23T14:13:40",
      "sentiment": "negative",
      "sentiment_score": -0.936,
      "sentiment_confidence": 0.936,
      "relevance_score": 1.0,
      "event_type": null
    },
    {
      "headline": "Nike vs. Lululemon: One Brand Is Losing Its Cool \u2014 and Investors Are Paying for It",
      "source": "Yahoo",
      "url": "https://finnhub.io/api/news?id=06c1a2f83bd174c139f8385ac88af67f24bcc687fc80edf3e72328d9587be8b5",
      "published_at": "2026-04-23T14:05:21",
      "sentiment": "negative",
      "sentiment_score": -0.945,
      "sentiment_confidence": 0.945,
      "relevance_score": 1.0,
      "event_type": null
    },
    {
      "headline": "Stocks making the biggest moves midday: Texas Instruments, United Rentals, Wex, Penn Entertainment & more",
      "source": "CNBC",
      "url": "https://finnhub.io/api/news?id=58536ec5b75132ed4cdf410647ccf1372d6cd6f792802281fdd34cc4b1211c65",
      "published_at": "2026-04-23T13:12:26",
      "sentiment": "neutral",
      "sentiment_score": 0.0,
      "sentiment_confidence": 0.85,
      "relevance_score": 1.0,
      "event_type": null
    },
    {
      "headline": "Here is What to Know Beyond Why NIKE, Inc. (NKE) is a Trending Stock",
      "source": "Yahoo",
      "url": "https://finnhub.io/api/news?id=0c29e3fe4ec0eb12ad4e8fb3d67cd1bfaab38d781b09377e359628449c862c48",
      "published_at": "2026-04-23T13:00:09",
      "sentiment": "neutral",
      "sentiment_score": 0.0,
      "sentiment_confidence": 0.921,
      "relevance_score": 1.0,
      "event_type": null
    },
    {
      "headline": "Lululemon names former Nike exec Heidi O'Neill as CEO",
      "source": "Yahoo",
      "url": "https://finnhub.io/api/news?id=15d934998b6a77fd662097a3f61b4f1f3d2a56b171260ece5d61717004c5b18c",
      "published_at": "2026-04-23T11:39:59",
      "sentiment": "neutral",
      "sentiment_score": 0.0,
      "sentiment_confidence": 0.932,
      "relevance_score": 1.0,
      "event_type": null
    },
    {
      "headline": "Lululemon appoints former Nike executive as next CEO",
      "source": "Yahoo",
      "url": "https://finnhub.io/api/news?id=af8f2623607dde038459ccc2c9615c87331118d637b2d4a3c05e7165b8cca3fb",
      "published_at": "2026-04-23T11:11:58",
      "sentiment": "neutral",
      "sentiment_score": 0.0,
      "sentiment_confidence": 0.897,
      "relevance_score": 1.0,
      "event_type": null
    },
    {
      "headline": "Lululemon Athletica New CEO Pick Triggers Transition Jitters, Stock Slides",
      "source": "Benzinga",
      "url": "https://finnhub.io/api/news?id=8afdb147a5f7e0a0f691895974ab59ea474fb2d6b3c622d5b4c2d9cf29aca94b",
      "published_at": "2026-04-23T10:51:21",
      "sentiment": "neutral",
      "sentiment_score": 0.0,
      "sentiment_confidence": 0.795,
      "relevance_score": 1.0,
      "event_type": null
    },
    {
      "headline": "Fed Rate Raise, Pause, Or Cut At Next Week's Meeting?",
      "source": "SeekingAlpha",
      "url": "https://finnhub.io/api/news?id=9cf7bdfed76a139746c11298ba465cb60d3c7bdf3a18143ffa239745b11cdbc6",
      "published_at": "2026-04-23T08:00:00",
      "sentiment": "neutral",
      "sentiment_score": 0.0,
      "sentiment_confidence": 0.516,
      "relevance_score": 1.0,
      "event_type": null
    },
    {
      "headline": "Stocks making the biggest moves premarket: Honeywell, Nokia, Netflix, IBM, Tesla & more",
      "source": "CNBC",
      "url": "https://finnhub.io/api/news?id=916efbf8f7b0750d74ad97ab6bdbb9d7b6f82c6125c9423044ccadb7899f7547",
      "published_at": "2026-04-23T07:16:42",
      "sentiment": "neutral",
      "sentiment_score": 0.0,
      "sentiment_confidence": 0.878,
      "relevance_score": 1.0,
      "event_type": null
    },
    {
      "headline": "Lululemon hires former Nike executive Heidi O'Neill to be its next CEO",
      "source": "CNBC",
      "url": "https://finnhub.io/api/news?id=4c918235fb2d84fa5d616c0f9a25535ce1642f162e6256837cbcd37d4ca69620",
      "published_at": "2026-04-23T07:07:59",
      "sentiment": "neutral",
      "sentiment_score": 0.0,
      "sentiment_confidence": 0.932,
      "relevance_score": 1.0,
      "event_type": null
    },
    {
      "headline": "PRESS DIGEST- New York Times business news - April 23",
      "source": "Finnhub",
      "url": "https://finnhub.io/api/news?id=fbd69010a10987eb70af1f9090f8e02c52e2b9e4bf817abe79287566d2d43637",
      "published_at": "2026-04-23T03:49:21",
      "sentiment": "neutral",
      "sentiment_score": 0.0,
      "sentiment_confidence": 0.921,
      "relevance_score": 1.0,
      "event_type": null
    },
    {
      "headline": "Tim Cook May Have Bought Nike Stock, But The Sneaker Giant Faces Potential 'Generational Reset,' Says This Analyst",
      "source": "Benzinga",
      "url": "https://finnhub.io/api/news?id=aa7a1c705d9cff4173bc9ff430ef3e95f3286fe4db32b9f76ffa1e75b64bd179",
      "published_at": "2026-04-23T02:30:24",
      "sentiment": "negative",
      "sentiment_score": -0.861,
      "sentiment_confidence": 0.861,
      "relevance_score": 1.0,
      "event_type": null
    },
    {
      "headline": "Lululemon Names Former Nike Executive as Its CEO. The Stock Is Down.",
      "source": "Yahoo",
      "url": "https://finnhub.io/api/news?id=9a8255c8077ff7210b2e72994e857e946f1f490de363bcc23d19d6fe988efc21",
      "published_at": "2026-04-22T22:53:00",
      "sentiment": "negative",
      "sentiment_score": -0.646,
      "sentiment_confidence": 0.646,
      "relevance_score": 1.0,
      "event_type": null
    },
    {
      "headline": "Lululemon stock sinks as athleisure company selects Nike veteran as new CEO",
      "source": "Yahoo",
      "url": "https://finnhub.io/api/news?id=d8ae9ea29e7d38a56939562de959fd453cdc5b87acdba6d5e1c74244be2d78b4",
      "published_at": "2026-04-22T21:14:09",
      "sentiment": "neutral",
      "sentiment_score": 0.0,
      "sentiment_confidence": 0.875,
      "relevance_score": 1.0,
      "event_type": null
    },
    {
      "headline": "Market reacts coolly as Lululemon taps ex-Nike exec Heidi O\u2019Neill for top job",
      "source": "Yahoo",
      "url": "https://finnhub.io/api/news?id=2da002c3da981039cd5aee7e5e4863fd846eff7372f4470aed5cee6b06667794",
      "published_at": "2026-04-22T21:01:28",
      "sentiment": "positive",
      "sentiment_score": 0.558,
      "sentiment_confidence": 0.558,
      "relevance_score": 1.0,
      "event_type": null
    },
    {
      "headline": "Lululemon taps former Nike executive to be next CEO",
      "source": "Yahoo",
      "url": "https://finnhub.io/api/news?id=7aab39f3496947a7a966fb3ae91550e992a9f3cf37678a7d8d3e1fd28de3aed5",
      "published_at": "2026-04-22T20:57:24",
      "sentiment": "neutral",
      "sentiment_score": 0.0,
      "sentiment_confidence": 0.933,
      "relevance_score": 1.0,
      "event_type": null
    },
    {
      "headline": "Lululemon Names Nike Veteran Heidi O\u2019Neill as Next CEO",
      "source": "Yahoo",
      "url": "https://finnhub.io/api/news?id=6c855d95fa9c5afd0604a361e4df95fa971cb3752a911a4d69da25a60c46ccaa",
      "published_at": "2026-04-22T20:42:05",
      "sentiment": "neutral",
      "sentiment_score": 0.0,
      "sentiment_confidence": 0.941,
      "relevance_score": 1.0,
      "event_type": null
    },
    {
      "headline": "Puma Hires New Wholesale and Sportstyle Leaders as It Continues Turnaround",
      "source": "Yahoo",
      "url": "https://finnhub.io/api/news?id=c6cadde61ef415a1f3c0a9c201f727e29583259dfdf03d7444cdd5004d104156",
      "published_at": "2026-04-22T18:00:51",
      "sentiment": "positive",
      "sentiment_score": 0.674,
      "sentiment_confidence": 0.674,
      "relevance_score": 1.0,
      "event_type": null
    },
    {
      "headline": "NIKE vs. adidas: Which Athletic Leader Deserves Investors' Attention?",
      "source": "Yahoo",
      "url": "https://finnhub.io/api/news?id=6d35b9c44d6e8fe203478fb4b1a61a78b041b9be04b8611da9a651a8d5b8add1",
      "published_at": "2026-04-22T17:00:00",
      "sentiment": "neutral",
      "sentiment_score": 0.0,
      "sentiment_confidence": 0.917,
      "relevance_score": 1.0,
      "event_type": null
    },
    {
      "headline": "Lululemon Stock Slides After Company Names New CEO",
      "source": "Benzinga",
      "url": "https://finnhub.io/api/news?id=ce3dcb2ec24eea30375e62212d6723f135f2385f5161f9a2dfd0d2559051d3af",
      "published_at": "2026-04-22T16:55:39",
      "sentiment": "negative",
      "sentiment_score": -0.897,
      "sentiment_confidence": 0.897,
      "relevance_score": 1.0,
      "event_type": null
    },
    {
      "headline": "Lululemon names former Nike exec Heidi O'Neill as new CEO",
      "source": "CNBC",
      "url": "https://finnhub.io/api/news?id=b431346bd5f873b48ddd8719b7c7c3c8b37540fbe5e9ea1ebd5263806c4fb7f4",
      "published_at": "2026-04-22T16:43:30",
      "sentiment": "neutral",
      "sentiment_score": 0.0,
      "sentiment_confidence": 0.919,
      "relevance_score": 1.0,
      "event_type": null
    },
    {
      "headline": "Lululemon names Nike vet Heidi O\u2019Neill CEO",
      "source": "Yahoo",
      "url": "https://finnhub.io/api/news?id=2a09be2007857129fddc7f4d11df630d51d45d9a2028d09a7f7da5ff2f2c24c2",
      "published_at": "2026-04-22T16:25:00",
      "sentiment": "neutral",
      "sentiment_score": 0.0,
      "sentiment_confidence": 0.931,
      "relevance_score": 1.0,
      "event_type": null
    },
    {
      "headline": "Lululemon picks former Nike executive Heidi O'Neill to be next CEO, executives say - WSJ",
      "source": "Finnhub",
      "url": "https://finnhub.io/api/news?id=fba54607fb88a1b64b9bb8912f4d7754f81dcc69e96651e0bb40a938b7fa1748",
      "published_at": "2026-04-22T16:01:19",
      "sentiment": "neutral",
      "sentiment_score": 0.0,
      "sentiment_confidence": 0.935,
      "relevance_score": 1.0,
      "event_type": null
    },
    {
      "headline": "Nike's Turnaround Is Still Not Complete. At Least, Not Until It Solves This Problem.",
      "source": "Yahoo",
      "url": "https://finnhub.io/api/news?id=5fde0bff8ec64aa392b10c114ba362d285ab6974697f534f73f80338cb635d43",
      "published_at": "2026-04-22T14:05:00",
      "sentiment": "neutral",
      "sentiment_score": 0.0,
      "sentiment_confidence": 0.687,
      "relevance_score": 1.0,
      "event_type": null
    },
    {
      "headline": "10 Consumer Discretionary Stocks With Whale Alerts In Today's Session",
      "source": "Benzinga",
      "url": "https://finnhub.io/api/news?id=9e5d1010bcdee9898fee31076cb1585d558bafc181ce098df200d1dd389d7cff",
      "published_at": "2026-04-22T13:35:49",
      "sentiment": "neutral",
      "sentiment_score": 0.0,
      "sentiment_confidence": 0.884,
      "relevance_score": 1.0,
      "event_type": null
    },
    {
      "headline": "Lightning Round: Buy Levi Strauss",
      "source": "CNBC",
      "url": "https://finnhub.io/api/news?id=d4f3ad9a9441e39aac8279ba47411e949e6b5036cd49536f64c6124f02a62f6d",
      "published_at": "2026-04-21T19:54:49",
      "sentiment": "neutral",
      "sentiment_score": 0.0,
      "sentiment_confidence": 0.903,
      "relevance_score": 1.0,
      "event_type": null
    },
    {
      "headline": "Jim Cramer explains why you trade on fundamentals, not fear",
      "source": "CNBC",
      "url": "https://finnhub.io/api/news?id=df1b18d7cb94af88aec83a5b2fef0c8eeac25c51d2c9854ce4681af4362f7259",
      "published_at": "2026-04-21T19:43:13",
      "sentiment": "neutral",
      "sentiment_score": 0.0,
      "sentiment_confidence": 0.931,
      "relevance_score": 1.0,
      "event_type": null
    },
    {
      "headline": "Nike Picked Stock of the Week at Smart Insider Following Renewed Insider Buying",
      "source": "Yahoo",
      "url": "https://finnhub.io/api/news?id=60d7b040b85bf7a97050e870442d3873284d951db5e92cc0cc732ae8afd629cb",
      "published_at": "2026-04-21T14:30:20",
      "sentiment": "positive",
      "sentiment_score": 0.487,
      "sentiment_confidence": 0.487,
      "relevance_score": 1.0,
      "event_type": null
    },
    {
      "headline": "NIKE INC : DZ Bank reaffirms its Buy rating",
      "source": "Finnhub",
      "url": "https://finnhub.io/api/news?id=c821be99f13fef72b0b468f1fe5185beac21e791fc15c21123629c5962b41f46",
      "published_at": "2026-04-21T09:06:16",
      "sentiment": "neutral",
      "sentiment_score": 0.0,
      "sentiment_confidence": 0.533,
      "relevance_score": 1.0,
      "event_type": null
    },
    {
      "headline": "Tariffs, Oil Shocks, and Volatility: Is Nike Still Worth Owning in 2026?",
      "source": "Yahoo",
      "url": "https://finnhub.io/api/news?id=e7baf14a44a5ffad467969ed8678468b79f939977c0565d3640470d6b2d89ead",
      "published_at": "2026-04-21T08:25:00",
      "sentiment": "neutral",
      "sentiment_score": 0.0,
      "sentiment_confidence": 0.915,
      "relevance_score": 1.0,
      "event_type": null
    },
    {
      "headline": "Apple's next CEO, Warsh's confirmation hearing, the psychedelic stock surge and more in Morning Squawk",
      "source": "CNBC",
      "url": "https://finnhub.io/api/news?id=a210602f291a54b603b54330f40904577be2bef799413ad6adabb90a9f161f61",
      "published_at": "2026-04-21T08:21:46",
      "sentiment": "neutral",
      "sentiment_score": 0.0,
      "sentiment_confidence": 0.7,
      "relevance_score": 1.0,
      "event_type": null
    },
    {
      "headline": "Is a Dividend Cut Inevitable for Nike?",
      "source": "Yahoo",
      "url": "https://finnhub.io/api/news?id=eb9530efd8e3fa053e990cbe9c069e617f5ed36bcd885dbd7169b028f509211c",
      "published_at": "2026-04-20T21:20:00",
      "sentiment": "neutral",
      "sentiment_score": 0.0,
      "sentiment_confidence": 0.662,
      "relevance_score": 1.0,
      "event_type": null
    },
    {
      "headline": "Most Softline Retailers Poised to Meet or Top Quarterly Earnings Views, UBS Says",
      "source": "Yahoo",
      "url": "https://finnhub.io/api/news?id=5f9b4c4a2344a7f661f3339e4de66d149d14cc7cc00cef62d478ec57f33d61a4",
      "published_at": "2026-04-20T19:59:33",
      "sentiment": "positive",
      "sentiment_score": 0.926,
      "sentiment_confidence": 0.926,
      "relevance_score": 1.0,
      "event_type": null
    },
    {
      "headline": "Are NIKE's Inventory Fixes Boosting Global Profitability Yet?",
      "source": "Yahoo",
      "url": "https://finnhub.io/api/news?id=25efe830ea96de433de3fd0f2e2aebfa068a1be6a46e6fcafc3cb84559f2b4a0",
      "published_at": "2026-04-20T16:24:00",
      "sentiment": "positive",
      "sentiment_score": 0.856,
      "sentiment_confidence": 0.856,
      "relevance_score": 1.0,
      "event_type": null
    },
    {
      "headline": "Insider Trades: Nike Sees More CEO Buys, Aehr Sold on 300% Gain",
      "source": "Yahoo",
      "url": "https://finnhub.io/api/news?id=60b9613dac7a6880c029ac529e60e78e731ef289d7d2f87caca1eab7d4f23975",
      "published_at": "2026-04-20T16:15:00",
      "sentiment": "positive",
      "sentiment_score": 0.634,
      "sentiment_confidence": 0.634,
      "relevance_score": 1.0,
      "event_type": null
    }
  ]
}