{
  "ticker": "PEP",
  "articles": [
    {
      "headline": "Pepsi Stock: Buy Before Q2 Earnings or Is Coca-Cola the Better Investment?",
      "source": "Yahoo",
      "url": "https://finnhub.io/api/news?id=37f0ce51ac54d3eb8fc05334ce4401d2e6cf6ca1a08218b05d9b7fc9a2f6e0d6",
      "published_at": "2026-07-07T22:51:00",
      "sentiment": "neutral",
      "sentiment_score": 0.0,
      "sentiment_confidence": 0.921,
      "relevance_score": 1.0,
      "event_type": null
    },
    {
      "headline": "Mark Cuban Once Described Teaching Disco at Sorority Houses for $25 an Hour as the 'Best Job Ever': Here's Why He'd Do It Again",
      "source": "Yahoo",
      "url": "https://finnhub.io/api/news?id=0d1c3565aaeb680b22af12e3785303bc15abbd37945ee4affbf111b1f7a481dd",
      "published_at": "2026-07-07T20:31:16",
      "sentiment": "neutral",
      "sentiment_score": 0.0,
      "sentiment_confidence": 0.907,
      "relevance_score": 1.0,
      "event_type": null
    },
    {
      "headline": "Chips Slip Again as Caterpillar Bites the Dow: Stock Market Today",
      "source": "Yahoo",
      "url": "https://finnhub.io/api/news?id=b31f9029ef1213512ec40bd2e03e4aefc7c602107816a68cd408ca975ef3f086",
      "published_at": "2026-07-07T20:06:34",
      "sentiment": "negative",
      "sentiment_score": -0.944,
      "sentiment_confidence": 0.944,
      "relevance_score": 1.0,
      "event_type": null
    },
    {
      "headline": "Here\u2019s How Much PepsiCo Stock Is Expected to Move After Earnings",
      "source": "Yahoo",
      "url": "https://finnhub.io/api/news?id=3fe78b6195bcacfbb3daaf5c52bb7b6e23f81eb3cfaab6e3897cc512f743d7c7",
      "published_at": "2026-07-07T13:11:18",
      "sentiment": "neutral",
      "sentiment_score": 0.0,
      "sentiment_confidence": 0.943,
      "relevance_score": 1.0,
      "event_type": null
    },
    {
      "headline": "Walmart cuts summer grocery prices, Trump claims credit",
      "source": "CNBC",
      "url": "https://finnhub.io/api/news?id=5fa2213ade8cff22eac2e57cdb7b91c7f64d1cc450d2731ed0b672e384e55b26",
      "published_at": "2026-07-07T12:36:25",
      "sentiment": "negative",
      "sentiment_score": -0.912,
      "sentiment_confidence": 0.912,
      "relevance_score": 1.0,
      "event_type": null
    },
    {
      "headline": "Walmart cuts prices on barbecue essentials after Trump highlights retailer\u2019s move (WMT)",
      "source": "Yahoo",
      "url": "https://finnhub.io/api/news?id=2fca687f09e28e1705b8b9366ed124c102210246d492fe6a5fc96fd7fb19442f",
      "published_at": "2026-07-07T10:45:03",
      "sentiment": "negative",
      "sentiment_score": -0.921,
      "sentiment_confidence": 0.921,
      "relevance_score": 1.0,
      "event_type": null
    },
    {
      "headline": "The Zacks Analyst Blog Highlights PepsiCo, Delta Air Lines, Bloom Energy, Ross Stores and NetEase",
      "source": "Yahoo",
      "url": "https://finnhub.io/api/news?id=fba53507398b57b558a55cb4429c379a6e778e80d2c4ca7499324aedea831a12",
      "published_at": "2026-07-07T10:09:00",
      "sentiment": "neutral",
      "sentiment_score": 0.0,
      "sentiment_confidence": 0.945,
      "relevance_score": 1.0,
      "event_type": null
    },
    {
      "headline": "June Dividend Raises From 6 Companies - 3 Are Undervalued Buys",
      "source": "SeekingAlpha",
      "url": "https://finnhub.io/api/news?id=b19e9f4e6443735bc63dae62075f7af375804016e62f81edd59657c1ef3262b9",
      "published_at": "2026-07-07T10:03:07",
      "sentiment": "positive",
      "sentiment_score": 0.568,
      "sentiment_confidence": 0.568,
      "relevance_score": 1.0,
      "event_type": null
    },
    {
      "headline": "Trump claims credit as Walmart drops prices on barbecue staples",
      "source": "Yahoo",
      "url": "https://finnhub.io/api/news?id=84bc8ccae5961c298c60d69dfda422b769f72f6d5a101bc7aa1cc5f80dde3248",
      "published_at": "2026-07-07T07:24:37",
      "sentiment": "negative",
      "sentiment_score": -0.963,
      "sentiment_confidence": 0.963,
      "relevance_score": 1.0,
      "event_type": null
    },
    {
      "headline": "PepsiCo (PEP) Launches RegenLend And Captain D's Seafood Promotion",
      "source": "Yahoo",
      "url": "https://finnhub.io/api/news?id=17402a8c23072f4fa2f484dd37cd0a5824cc3292ee09889c1b36f35f971b4425",
      "published_at": "2026-07-06T21:09:16",
      "sentiment": "neutral",
      "sentiment_score": 0.0,
      "sentiment_confidence": 0.88,
      "relevance_score": 1.0,
      "event_type": null
    },
    {
      "headline": "Update: Dow Crosses 53,000, Nasdaq Rebounds as Tech Advances",
      "source": "Yahoo",
      "url": "https://finnhub.io/api/news?id=c88e49868d85fc5cfb4fe609aa0ccba72e8e97490f9fb8b121cb09d41cda7c96",
      "published_at": "2026-07-06T20:57:23",
      "sentiment": "negative",
      "sentiment_score": -0.53,
      "sentiment_confidence": 0.53,
      "relevance_score": 1.0,
      "event_type": null
    },
    {
      "headline": "If you can spy a rotation and theme, you can find some incredible bargains: Cramer",
      "source": "CNBC",
      "url": "https://finnhub.io/api/news?id=9ce6511b530cefc027b673588d40c431455d9b6ec92b8b9007205225a2fedb73",
      "published_at": "2026-07-06T19:27:09",
      "sentiment": "neutral",
      "sentiment_score": 0.0,
      "sentiment_confidence": 0.896,
      "relevance_score": 1.0,
      "event_type": null
    },
    {
      "headline": "Update: Equity Markets Rise Intraday as Tech Advances",
      "source": "Yahoo",
      "url": "https://finnhub.io/api/news?id=e6caea5d730cbb96148c0cae01c6f3f7b20ff39c70a5d42e9ca8bfc35586cf76",
      "published_at": "2026-07-06T18:10:53",
      "sentiment": "positive",
      "sentiment_score": 0.93,
      "sentiment_confidence": 0.93,
      "relevance_score": 1.0,
      "event_type": null
    },
    {
      "headline": "Ex-PepsiCo CEO Indra Nooyi worked from midnight until 5 a.m. as a receptionist to pay for her Yale degree\u2014and she says \u2018respect went up\u2019 because of it",
      "source": "Yahoo",
      "url": "https://finnhub.io/api/news?id=30e1ba3c1e467fb5709197dabd5942f938c4af65fb639df9ac80b42a58ff0896",
      "published_at": "2026-07-06T16:01:06",
      "sentiment": "neutral",
      "sentiment_score": 0.0,
      "sentiment_confidence": 0.502,
      "relevance_score": 1.0,
      "event_type": null
    },
    {
      "headline": "Wall Street braces for Fed signals as earnings season gets underway",
      "source": "Yahoo",
      "url": "https://finnhub.io/api/news?id=b0eb1e93c323d50bdfc9eef3683d1c18c58b4caad3aa33f30f88e0f32b9cd036",
      "published_at": "2026-07-06T14:20:00",
      "sentiment": "neutral",
      "sentiment_score": 0.0,
      "sentiment_confidence": 0.744,
      "relevance_score": 1.0,
      "event_type": null
    },
    {
      "headline": "Coca-Cola Just Hit an All-Time High -- and Pepsi Trades 16% Below Its 52-Week High. Which Dividend Giant Is the Better Buy?",
      "source": "Yahoo",
      "url": "https://finnhub.io/api/news?id=8201f0d72ff5d5a8ed4bbba219073bfa18acdd198cc0b4efcd248693db4a6826",
      "published_at": "2026-07-06T13:26:00",
      "sentiment": "negative",
      "sentiment_score": -0.729,
      "sentiment_confidence": 0.729,
      "relevance_score": 1.0,
      "event_type": null
    },
    {
      "headline": "5 Things to Know Before the Stock Market Opens on Monday",
      "source": "Yahoo",
      "url": "https://finnhub.io/api/news?id=c2e69e87190bbfc1c26d17962a00b3cec1c24e48bec30d99ac6ca5d1aabd4240",
      "published_at": "2026-07-06T12:25:23",
      "sentiment": "neutral",
      "sentiment_score": 0.0,
      "sentiment_confidence": 0.932,
      "relevance_score": 1.0,
      "event_type": null
    },
    {
      "headline": "Nasdaq starts strong as 'Trump accounts' launch, Dow dragged down",
      "source": "Yahoo",
      "url": "https://finnhub.io/api/news?id=9389013d71fe7c5c0a0407bec65a9b6249337d8cc91deeb91588cd3ef1be3380",
      "published_at": "2026-07-06T11:59:00",
      "sentiment": "positive",
      "sentiment_score": 0.818,
      "sentiment_confidence": 0.818,
      "relevance_score": 1.0,
      "event_type": null
    },
    {
      "headline": "Equities Mostly Rise Pre-Bell as Investors Prepare for Fed Minutes",
      "source": "Yahoo",
      "url": "https://finnhub.io/api/news?id=cc375bfcac236103e0c7169601f6776ae6e3c642fca7663ff366182467c31237",
      "published_at": "2026-07-06T11:53:02",
      "sentiment": "neutral",
      "sentiment_score": 0.0,
      "sentiment_confidence": 0.503,
      "relevance_score": 1.0,
      "event_type": null
    },
    {
      "headline": "US Equity Investors to Tune into Fed's Meeting Minutes Amid Expectations for Higher Interest Rates, Geopolitical Developments",
      "source": "Yahoo",
      "url": "https://finnhub.io/api/news?id=0a6e69eeae66cf5af6c5c578689987784de6c100c26fd1e0b4c874e35fb8888d",
      "published_at": "2026-07-06T10:13:46",
      "sentiment": "neutral",
      "sentiment_score": 0.0,
      "sentiment_confidence": 0.626,
      "relevance_score": 1.0,
      "event_type": null
    },
    {
      "headline": "Why You Want PepsiCo To Miss Earnings This Week",
      "source": "SeekingAlpha",
      "url": "https://finnhub.io/api/news?id=cd561304fa3016a7150cea90dd15b53861ae23b28c1c7c450da46bbe7887db83",
      "published_at": "2026-07-06T09:06:20",
      "sentiment": "negative",
      "sentiment_score": -0.893,
      "sentiment_confidence": 0.893,
      "relevance_score": 1.0,
      "event_type": null
    },
    {
      "headline": "Nasdaq, S&P 500, Dow Futures Kick Off Fresh Week On Strong Note: Why META, NVDA, MU, IREN, PEP, HOOD Are In Focus",
      "source": "Yahoo",
      "url": "https://finnhub.io/api/news?id=211bd25345e671685dced726b19b0182ba19f6fdf37d229e6d0b0611bff042de",
      "published_at": "2026-07-06T08:41:17",
      "sentiment": "positive",
      "sentiment_score": 0.657,
      "sentiment_confidence": 0.657,
      "relevance_score": 1.0,
      "event_type": null
    },
    {
      "headline": "Trump exclusive, prediction market activity soars, AI Alexander Hamilton and more in Morning Squawk",
      "source": "CNBC",
      "url": "https://finnhub.io/api/news?id=f704e5b616a8f9d9539976db9c86efbc1220676918c6359493ce2a8b0c1f761e",
      "published_at": "2026-07-06T08:04:11",
      "sentiment": "neutral",
      "sentiment_score": 0.0,
      "sentiment_confidence": 0.902,
      "relevance_score": 1.0,
      "event_type": null
    },
    {
      "headline": "PEP Stock Faces Fresh Pressure: Barclays Cuts Price Target, Warns Turnaround Is Losing Steam Ahead Of Q2 Earnings",
      "source": "Yahoo",
      "url": "https://finnhub.io/api/news?id=28a5e6e06967d106b038d179e2b58fa6ac3768e40de988bf58cdde444ed3a78e",
      "published_at": "2026-07-06T07:07:53",
      "sentiment": "negative",
      "sentiment_score": -0.966,
      "sentiment_confidence": 0.966,
      "relevance_score": 1.0,
      "event_type": null
    },
    {
      "headline": "Stock Market Today: Dow Jones Futures Fall,  S&P 500, Nasdaq Gain Following Independence Day Weekend\u2014 Intel, SanDisk, Tesla, Ford In Focus (UPDATED)",
      "source": "Benzinga",
      "url": "https://finnhub.io/api/news?id=74deaa10ff9f8b780c61d5883c7bb9496270cb02ec011222cca520d52648acf1",
      "published_at": "2026-07-06T05:23:00",
      "sentiment": "negative",
      "sentiment_score": -0.85,
      "sentiment_confidence": 0.85,
      "relevance_score": 1.0,
      "event_type": null
    },
    {
      "headline": "Stock Futures Open Mixed, Kicking Off Week that Includes Fed Minutes",
      "source": "Yahoo",
      "url": "https://finnhub.io/api/news?id=69ef475f44b901376206ea1bf832a5a23c95b0c1a9de9d0cf4b73128f6ede13a",
      "published_at": "2026-07-05T22:37:00",
      "sentiment": "negative",
      "sentiment_score": -0.803,
      "sentiment_confidence": 0.803,
      "relevance_score": 1.0,
      "event_type": null
    },
    {
      "headline": "Stock Futures Kick Off Week that Includes Fed Minutes",
      "source": "Yahoo",
      "url": "https://finnhub.io/api/news?id=f7dea206806c0f816f641f88c4de99dc5dcf723a579865084ee7f38c72831678",
      "published_at": "2026-07-05T20:56:00",
      "sentiment": "neutral",
      "sentiment_score": 0.0,
      "sentiment_confidence": 0.83,
      "relevance_score": 1.0,
      "event_type": null
    },
    {
      "headline": "Coca-Cola Is Crushing the Nasdaq and S&P 500 in 2026, but This Higher-Yield Dividend King Could Be an Even Better Stock to Buy for the Second Half of 2026",
      "source": "Yahoo",
      "url": "https://finnhub.io/api/news?id=51c46459081bf0de6e23808067203691d6d0d8389e19bf2b5d84e546a19721ef",
      "published_at": "2026-07-05T18:25:00",
      "sentiment": "positive",
      "sentiment_score": 0.841,
      "sentiment_confidence": 0.841,
      "relevance_score": 1.0,
      "event_type": null
    },
    {
      "headline": "Fed Minutes, Home Sales, Pepsi, Delta, and More to Watch This Week",
      "source": "Yahoo",
      "url": "https://finnhub.io/api/news?id=f75de98fea683889e8befada134318b7f101f2cc37cdcdd89f9b812de6c01082",
      "published_at": "2026-07-05T18:00:00",
      "sentiment": "neutral",
      "sentiment_score": 0.0,
      "sentiment_confidence": 0.934,
      "relevance_score": 1.0,
      "event_type": null
    },
    {
      "headline": "Tech Rotation, FOMC and Other Key Things to Watch this Week",
      "source": "Yahoo",
      "url": "https://finnhub.io/api/news?id=408a42c2ec95594034d178e7ebadd61bb6d3d7cec8e9ad6ffc2189f1978a4c45",
      "published_at": "2026-07-05T17:00:02",
      "sentiment": "neutral",
      "sentiment_score": 0.0,
      "sentiment_confidence": 0.939,
      "relevance_score": 1.0,
      "event_type": null
    },
    {
      "headline": "Top Three Catalysts That Could Move the S&P 500 and Dow This Week",
      "source": "Benzinga",
      "url": "https://finnhub.io/api/news?id=3ff72e5d97fe269603687b723a46b400ab534e677b11d9b3315a72daf2210a21",
      "published_at": "2026-07-05T16:11:12",
      "sentiment": "neutral",
      "sentiment_score": 0.0,
      "sentiment_confidence": 0.9,
      "relevance_score": 1.0,
      "event_type": null
    },
    {
      "headline": "Rate hike readjustment and AI hardware momentum: What to watch this week",
      "source": "Yahoo",
      "url": "https://finnhub.io/api/news?id=a481fb22e12403af412bffbb1ebe0012b24b4884f0a0642316425ea5e5b057cf",
      "published_at": "2026-07-05T16:00:59",
      "sentiment": "neutral",
      "sentiment_score": 0.0,
      "sentiment_confidence": 0.917,
      "relevance_score": 1.0,
      "event_type": null
    },
    {
      "headline": "A Dividend Portfolio That Out-Earns the Average California Family",
      "source": "Yahoo",
      "url": "https://finnhub.io/api/news?id=da86610afdada0f014b3f44c9f10b0f6e5a27d36c6acbe39c4ae95e2cd877a96",
      "published_at": "2026-07-05T15:30:56",
      "sentiment": "neutral",
      "sentiment_score": 0.0,
      "sentiment_confidence": 0.86,
      "relevance_score": 1.0,
      "event_type": null
    },
    {
      "headline": "How To Turn A Portfolio Into $500 A Month Without Chasing Dangerous Yields",
      "source": "Yahoo",
      "url": "https://finnhub.io/api/news?id=020dac214eca5b75b6cc359d40935d3716526866b7ff20aec95380bc0db56073",
      "published_at": "2026-07-05T13:52:19",
      "sentiment": "neutral",
      "sentiment_score": 0.0,
      "sentiment_confidence": 0.923,
      "relevance_score": 1.0,
      "event_type": null
    },
    {
      "headline": "Wall Street Brunch: Options Spy SpaceX Pop",
      "source": "SeekingAlpha",
      "url": "https://finnhub.io/api/news?id=a16525ed99c60f90accce500e5e005d8e06ebe6fb775797f2cb80065f26cf4e8",
      "published_at": "2026-07-05T12:25:00",
      "sentiment": "neutral",
      "sentiment_score": 0.0,
      "sentiment_confidence": 0.915,
      "relevance_score": 1.0,
      "event_type": null
    },
    {
      "headline": "Wall Street Week Ahead",
      "source": "SeekingAlpha",
      "url": "https://finnhub.io/api/news?id=e1484bac8e16dbda455fb97bb4007cad530b3e13d3bdbd81aa57edd4b424aa5f",
      "published_at": "2026-07-05T04:53:41",
      "sentiment": "neutral",
      "sentiment_score": 0.0,
      "sentiment_confidence": 0.767,
      "relevance_score": 1.0,
      "event_type": null
    },
    {
      "headline": "PepsiCo, Delta Air Lines To Report Earnings; FOMC's Meeting Minutes In Focus",
      "source": "SeekingAlpha",
      "url": "https://finnhub.io/api/news?id=aec5fdea10c9f314c71380ca0c9ee62e94d29addc7e8e8bb5081cb2ddcf57e08",
      "published_at": "2026-07-04T11:00:00",
      "sentiment": "neutral",
      "sentiment_score": 0.0,
      "sentiment_confidence": 0.928,
      "relevance_score": 1.0,
      "event_type": null
    },
    {
      "headline": "The Look Ahead: July 2, 2026",
      "source": "CNBC",
      "url": "https://finnhub.io/api/news?id=800d5555fce30f66c72eb3772b5ec72a0b8faa83f0afe9e4e62ea90f8611a598",
      "published_at": "2026-07-04T00:00:01",
      "sentiment": "neutral",
      "sentiment_score": 0.0,
      "sentiment_confidence": 0.944,
      "relevance_score": 1.0,
      "event_type": null
    },
    {
      "headline": "This Tech ETF Is Quietly Outperforming QQQ in 2026 -- Is There Still Time to Buy?",
      "source": "Yahoo",
      "url": "https://finnhub.io/api/news?id=9dd7c87cfb178b328fd1ef0da84675b911e4ee7330821c4f1f41eee234b0a682",
      "published_at": "2026-07-03T17:35:00",
      "sentiment": "negative",
      "sentiment_score": -0.409,
      "sentiment_confidence": 0.409,
      "relevance_score": 1.0,
      "event_type": null
    },
    {
      "headline": "Unlocking Q2 Potential of PepsiCo (PEP): Exploring Wall Street Estimates for Key Metrics",
      "source": "Yahoo",
      "url": "https://finnhub.io/api/news?id=5e5ed1c42a74524b5700f705bcd0755943a2f8d3406ba20f2c34fb84a7d3a4a3",
      "published_at": "2026-07-03T13:15:02",
      "sentiment": "neutral",
      "sentiment_score": 0.0,
      "sentiment_confidence": 0.696,
      "relevance_score": 1.0,
      "event_type": null
    },
    {
      "headline": "Coca-Cola Stock Hits 52-Week High: Time to Buy or Wait for Now?",
      "source": "Yahoo",
      "url": "https://finnhub.io/api/news?id=ab41575181f32a5a8bf86376af0d3bd2508fab1ce1452dc1521ed480f65fceeb",
      "published_at": "2026-07-03T12:35:00",
      "sentiment": "neutral",
      "sentiment_score": 0.0,
      "sentiment_confidence": 0.85,
      "relevance_score": 1.0,
      "event_type": null
    },
    {
      "headline": "PepsiCo Q2 Earnings Preview: Buy, Hold or Sell the Stock?",
      "source": "Yahoo",
      "url": "https://finnhub.io/api/news?id=79d979c97730fe29208c90e0c211ecdfca312081d5fad74ec81217a52d0133a1",
      "published_at": "2026-07-03T12:26:00",
      "sentiment": "neutral",
      "sentiment_score": 0.0,
      "sentiment_confidence": 0.913,
      "relevance_score": 1.0,
      "event_type": null
    },
    {
      "headline": "Trump\u2019s Freedom 250 draws corporate sponsors with business before his administration",
      "source": "CNBC",
      "url": "https://finnhub.io/api/news?id=c927f22cd5b05e3226e169110c87a08a0c2938775005633fad3fa3e91fcf437d",
      "published_at": "2026-07-03T08:00:01",
      "sentiment": "neutral",
      "sentiment_score": 0.0,
      "sentiment_confidence": 0.913,
      "relevance_score": 1.0,
      "event_type": null
    },
    {
      "headline": "Soda, Coffee, and Cava Won the First Half. Snacks and Pizza Struggled.",
      "source": "Yahoo",
      "url": "https://finnhub.io/api/news?id=91a14ee5d1a6dab5b6ac083158480a7491177be30dd8eac1bb3bbc12c45d5a17",
      "published_at": "2026-07-02T21:52:00",
      "sentiment": "negative",
      "sentiment_score": -0.915,
      "sentiment_confidence": 0.915,
      "relevance_score": 1.0,
      "event_type": null
    },
    {
      "headline": "PepsiCo (PEP) Stock Moves 2.17%: What You Should Know",
      "source": "Yahoo",
      "url": "https://finnhub.io/api/news?id=07999f3b0c91db60e392133ea407f91b010a0d41116f3de2547f26a0a0fe58d5",
      "published_at": "2026-07-02T21:50:04",
      "sentiment": "neutral",
      "sentiment_score": 0.0,
      "sentiment_confidence": 0.881,
      "relevance_score": 1.0,
      "event_type": null
    },
    {
      "headline": "The Portfolio That Could Put You in a New Car Every Year for Life",
      "source": "Yahoo",
      "url": "https://finnhub.io/api/news?id=fe78d437c94931ac256d57c13ae49ad082d1c56218345ec2a98db05b4445c452",
      "published_at": "2026-07-02T17:13:18",
      "sentiment": "neutral",
      "sentiment_score": 0.0,
      "sentiment_confidence": 0.915,
      "relevance_score": 1.0,
      "event_type": null
    },
    {
      "headline": "Coca-Cola vs. PepsiCo: Which Beverage Titan Is Adjusting to New Consumer Habits Better?",
      "source": "Yahoo",
      "url": "https://finnhub.io/api/news?id=319a5ffd138afebdd8836eb47d6a86d1d4d6f61990b1d5915705446a8f4bae88",
      "published_at": "2026-07-02T16:00:26",
      "sentiment": "neutral",
      "sentiment_score": 0.0,
      "sentiment_confidence": 0.797,
      "relevance_score": 1.0,
      "event_type": null
    },
    {
      "headline": "PepsiCo's Top Line Trends in North America Under Pressure for May, Early June, UBS Securities Says",
      "source": "Yahoo",
      "url": "https://finnhub.io/api/news?id=dc079a2343c2c2870f905ea897e67c52720fc7174a3f78cac91a15a7f00f9e22",
      "published_at": "2026-07-02T15:44:23",
      "sentiment": "neutral",
      "sentiment_score": 0.0,
      "sentiment_confidence": 0.495,
      "relevance_score": 1.0,
      "event_type": null
    },
    {
      "headline": "National Beverage Stock Jumps After LaCroix Owner Declares Special Dividend",
      "source": "Yahoo",
      "url": "https://finnhub.io/api/news?id=c75e8f8ed2d30791b88b4bec56f668c851c67a62071847d892e9fb6ee1702bbd",
      "published_at": "2026-07-02T15:29:00",
      "sentiment": "neutral",
      "sentiment_score": 0.0,
      "sentiment_confidence": 0.552,
      "relevance_score": 1.0,
      "event_type": null
    },
    {
      "headline": "$500 a Month in These Stocks Will Generate $6,700 in Passive Annual Income",
      "source": "Yahoo",
      "url": "https://finnhub.io/api/news?id=a60b16d0d67885632b53f8b7db33b97bba6bda6dfda573e80f8a5eb74776eba9",
      "published_at": "2026-07-02T15:02:53",
      "sentiment": "neutral",
      "sentiment_score": 0.0,
      "sentiment_confidence": 0.845,
      "relevance_score": 1.0,
      "event_type": null
    }
  ]
}